ColabComponent/Component.py
ColabComponent/__init__.py
ColabComponent-0.0.3.dist-info/LICENSE
ColabComponent-0.0.3.dist-info/METADATA
ColabComponent-0.0.3.dist-info/WHEEL
ColabComponent-0.0.3.dist-info/top_level.txt
ColabComponent-0.0.3.dist-info/RECORD
