Metadata-Version: 2.1
Name: ColabComponent
Version: 0.0.3
Summary: A React.js inspired Component for building a simple reactive UI in Google Colaboratory.
Home-page: https://github.com/PPierzc/ColabComponent
Author: Paweł A. Pierzchlewicz
Author-email: paul@teacode.io
License: MIT
Keywords: python,colab,react,ui,component
Platform: UNKNOWN
Classifier: Development Status :: 3 - Alpha
Classifier: Intended Audience :: Developers
Classifier: Topic :: Software Development :: Build Tools
Classifier: License :: OSI Approved :: MIT License
Classifier: Programming Language :: Python :: 3
